postimpressionism/Getimpressionism.py
postimpressionism/Postimpressionism.py
postimpressionism/Setimpressionism.py
postimpressionism/__init__.py
postimpressionism-0.1.7.dist-info/LICENSE
postimpressionism-0.1.7.dist-info/METADATA
postimpressionism-0.1.7.dist-info/WHEEL
postimpressionism-0.1.7.dist-info/top_level.txt
postimpressionism-0.1.7.dist-info/RECORD
