Metadata-Version: 2.1
Name: postimpressionism
Version: 0.1.7
Summary: An Art Exploration Package based on Modernist Avant-garde as a Post-Production of Digital Contemporary Art;
Home-page: https://github.com/AkiraDemenech/Postimpressionism
Author: Akira Demenech
Author-email: akira.demenech@gmail.com
License: MIT License
Keywords: art image postproduction postimpressionism
Platform: UNKNOWN
Classifier: Programming Language :: Python :: 3
Classifier: License :: OSI Approved :: MIT License
Classifier: Operating System :: OS Independent
License-File: LICENSE
Requires-Dist: matplotlib
Requires-Dist: numpy
Requires-Dist: Pillow
